{
  "basic_info": {
    "number": 1673,
    "title": "READMEの目次を更新：ステップ１産業に電子決済手数料の課題対応を明記 (えんどうかつひろさん提案)",
    "state": "open",
    "created_at": "2025-05-25T21:37:54Z",
    "updated_at": "2025-06-16T12:42:00Z",
    "closed_at": null,
    "merged_at": null,
    "html_url": "https://github.com/team-mirai/policy/pull/1673",
    "user": {
      "login": "idobata-policy-app[bot]",
      "id": 211775619,
      "html_url": "https://github.com/apps/idobata-policy-app"
    }
  },
  "labels": [
    {
      "id": 8631774158,
      "node_id": "LA_kwDOOqTJvM8AAAACAn5rzg",
      "url": "https://api.github.com/repos/team-mirai/policy/labels/%E7%94%A3%E6%A5%AD%E6%94%BF%E7%AD%96",
      "name": "産業政策",
      "color": "534FCF",
      "default": false,
      "description": ""
    }
  ],
  "comments": [],
  "review_comments": [],
  "files": [
    {
      "sha": "d32d34c10b96772b7454e5033ab21b44c9196bee",
      "filename": "README.md",
      "status": "modified",
      "additions": 2,
      "deletions": 1,
      "changes": 3,
      "blob_url": "https://github.com/team-mirai/policy/blob/71c21159328faf9951a1236d5b24f6351e4c93ce/README.md",
      "raw_url": "https://github.com/team-mirai/policy/raw/71c21159328faf9951a1236d5b24f6351e4c93ce/README.md",
      "contents_url": "https://api.github.com/repos/team-mirai/policy/contents/README.md?ref=71c21159328faf9951a1236d5b24f6351e4c93ce",
      "patch": "@@ -14,7 +14,7 @@\n   * [１．教育](11_ステップ１教育.md)  \n   * [２．子育て](12_ステップ１子育て.md)  \n   * [３．行政改革](13_ステップ１行政改革.md)  \n-  * [４．産業](14_ステップ１産業.md)  \n+  * [４．産業（電子決済手数料の課題対応を含む）](14_ステップ１産業.md)  \n   * [５．科学技術](15_ステップ１科学技術.md)  \n   * [６．デジタル民主主義](16_ステップ１デジタル民主主義.md)  \n   * [７．医療](17_ステップ１医療.md)  \n@@ -108,3 +108,4 @@\n ## おしゃべりできるシステム『いどばたシステム』について\n \n - [デジタル民主主義2030](https://dd2030.org)で開発した[『いどばた』](https://github.com/digitaldemocracy2030/idobata/)を活用しています\n+"
    }
  ],
  "commits": [
    {
      "sha": "71c21159328faf9951a1236d5b24f6351e4c93ce",
      "node_id": "C_kwDOOqTJvNoAKDcxYzIxMTU5MzI4ZmFmOTk1MWExMjM2ZDViMjRmNjM1MWU0YzkzY2U",
      "commit": {
        "author": {
          "name": "idobata-policy-app[bot]",
          "email": "211775619+idobata-policy-app[bot]@users.noreply.github.com",
          "date": "2025-05-25T21:34:58Z"
        },
        "committer": {
          "name": "GitHub",
          "email": "noreply@github.com",
          "date": "2025-05-25T21:34:58Z"
        },
        "message": "えんどうかつひろさんの提案に基づき、ステップ１産業の項目に電子決済手数料の課題対応を追記",
        "tree": {
          "sha": "9453be95adacda7d0923c481ff70b2e249c49005",
          "url": "https://api.github.com/repos/team-mirai/policy/git/trees/9453be95adacda7d0923c481ff70b2e249c49005"
        },
        "url": "https://api.github.com/repos/team-mirai/policy/git/commits/71c21159328faf9951a1236d5b24f6351e4c93ce",
        "comment_count": 0,
        "verification": {
          "verified": true,
          "reason": "valid",
          "signature": "-----BEGIN PGP SIGNATURE-----\n\nwsFcBAABCAAQBQJoM40CCRC1aQ7uu5UhlAAAGAEQABiG4ocHlPurH1ahlRGQa7zq\nHrdG6cQ993P3sqPrFY4DnZmB312K79XKRlL9paZT5F2VruSoIBBG7r/QGFzEDuHc\ndCWkVs0AxGAWenD2aRQHJ6brlFs3Dv8NWSLeVRAi0ZqN/W8JeSyOb0d0KerDN/hf\nTrzAYkJ114IwNodcZ0Vi9uU54b1yKPo3BjF9vLklEkO3Ca5n8ZCd6zlq2/B25IV+\nK7nbLjWJVoyC5/gKhbGypSF2j6yZ34fDDKPlkGcGfHoxtQR7Ygfu7qb+X8sm3evp\nIuPLJE+zXF1tFQoXxl0tPtD3zCWxrSfsUMswJiReKhBBcf0uryQnWUr6kMbzdgVc\nq2pdKUycOswTRNSHP+Dav/Rai72F9okrY1XLAyVrvlhB9WztGFLSmcCdT1kQaBMt\nIxvmXfCXlS/g14Z/DNAJgBNR0olIR+V/lHz4Ve94fvMUr6cdtltL69xFKs3VoKPW\nTvUpng4dhMWF6Nsu+TJJTilUbASyZ+0MqBJhmY4D2BpIlEB8zabwEDaaPobKEhco\n1iMUZ5BmaqZNLo6qgGthk4sQfmiJ0secegMertl944sFogKu4xcd+TRc4NdeIkft\n+c4YE6zzIjE1U1sBX7AcztSDmB7Mrt6edoOfKdj5NnwT739CNit0pv23wT4Sz4lz\nSLCqN4vztpcKrx4J0Cle\n=Uxte\n-----END PGP SIGNATURE-----\n",
          "payload": "tree 9453be95adacda7d0923c481ff70b2e249c49005\nparent 908eab9a58987d6d3b671172795b881bf0417658\nauthor idobata-policy-app[bot] <211775619+idobata-policy-app[bot]@users.noreply.github.com> 1748208898 +0000\ncommitter GitHub <noreply@github.com> 1748208898 +0000\n\nえんどうかつひろさんの提案に基づき、ステップ１産業の項目に電子決済手数料の課題対応を追記",
          "verified_at": "2025-05-25T21:34:58Z"
        }
      },
      "url": "https://api.github.com/repos/team-mirai/policy/commits/71c21159328faf9951a1236d5b24f6351e4c93ce",
      "html_url": "https://github.com/team-mirai/policy/commit/71c21159328faf9951a1236d5b24f6351e4c93ce",
      "comments_url": "https://api.github.com/repos/team-mirai/policy/commits/71c21159328faf9951a1236d5b24f6351e4c93ce/comments",
      "author": {
        "login": "idobata-policy-app[bot]",
        "id": 211775619,
        "node_id": "BOT_kgDODJ9wgw",
        "avatar_url": "https://avatars.githubusercontent.com/u/210232249?v=4",
        "gravatar_id": "",
        "url": "https://api.github.com/users/idobata-policy-app%5Bbot%5D",
        "html_url": "https://github.com/apps/idobata-policy-app",
        "followers_url": "https://api.github.com/users/idobata-policy-app%5Bbot%5D/followers",
        "following_url": "https://api.github.com/users/idobata-policy-app%5Bbot%5D/following{/other_user}",
        "gists_url": "https://api.github.com/users/idobata-policy-app%5Bbot%5D/gists{/gist_id}",
        "starred_url": "https://api.github.com/users/idobata-policy-app%5Bbot%5D/starred{/owner}{/repo}",
        "subscriptions_url": "https://api.github.com/users/idobata-policy-app%5Bbot%5D/subscriptions",
        "organizations_url": "https://api.github.com/users/idobata-policy-app%5Bbot%5D/orgs",
        "repos_url": "https://api.github.com/users/idobata-policy-app%5Bbot%5D/repos",
        "events_url": "https://api.github.com/users/idobata-policy-app%5Bbot%5D/events{/privacy}",
        "received_events_url": "https://api.github.com/users/idobata-policy-app%5Bbot%5D/received_events",
        "type": "Bot",
        "user_view_type": "public",
        "site_admin": false
      },
      "committer": {
        "login": "web-flow",
        "id": 19864447,
        "node_id": "MDQ6VXNlcjE5ODY0NDQ3",
        "avatar_url": "https://avatars.githubusercontent.com/u/19864447?v=4",
        "gravatar_id": "",
        "url": "https://api.github.com/users/web-flow",
        "html_url": "https://github.com/web-flow",
        "followers_url": "https://api.github.com/users/web-flow/followers",
        "following_url": "https://api.github.com/users/web-flow/following{/other_user}",
        "gists_url": "https://api.github.com/users/web-flow/gists{/gist_id}",
        "starred_url": "https://api.github.com/users/web-flow/starred{/owner}{/repo}",
        "subscriptions_url": "https://api.github.com/users/web-flow/subscriptions",
        "organizations_url": "https://api.github.com/users/web-flow/orgs",
        "repos_url": "https://api.github.com/users/web-flow/repos",
        "events_url": "https://api.github.com/users/web-flow/events{/privacy}",
        "received_events_url": "https://api.github.com/users/web-flow/received_events",
        "type": "User",
        "user_view_type": "public",
        "site_admin": false
      },
      "parents": [
        {
          "sha": "908eab9a58987d6d3b671172795b881bf0417658",
          "url": "https://api.github.com/repos/team-mirai/policy/commits/908eab9a58987d6d3b671172795b881bf0417658",
          "html_url": "https://github.com/team-mirai/policy/commit/908eab9a58987d6d3b671172795b881bf0417658"
        }
      ]
    }
  ],
  "collected_at": "2025-06-17T17:14:44.376193"
}