{
  "basic_info": {
    "number": 2264,
    "title": "木村準一さん提案：教員不足対策としての行政職からの人員再配置案の追加",
    "state": "open",
    "created_at": "2025-06-13T01:08:58Z",
    "updated_at": "2025-06-13T01:08:58Z",
    "closed_at": null,
    "merged_at": null,
    "html_url": "https://github.com/team-mirai/policy/pull/2264",
    "user": {
      "login": "idobata-policy-app[bot]",
      "id": 211775619,
      "html_url": "https://github.com/apps/idobata-policy-app"
    }
  },
  "labels": [],
  "comments": [],
  "review_comments": [],
  "files": [
    {
      "sha": "e54491ec400e054f8c0a97f88d7ed7d7a473139f",
      "filename": "11_ステップ１教育.md",
      "status": "modified",
      "additions": 2,
      "deletions": 1,
      "changes": 3,
      "blob_url": "https://github.com/team-mirai/policy/blob/4e5b5193e40106166d57a96e42a388417621358c/11_%E3%82%B9%E3%83%86%E3%83%83%E3%83%97%EF%BC%91%E6%95%99%E8%82%B2.md",
      "raw_url": "https://github.com/team-mirai/policy/raw/4e5b5193e40106166d57a96e42a388417621358c/11_%E3%82%B9%E3%83%86%E3%83%83%E3%83%97%EF%BC%91%E6%95%99%E8%82%B2.md",
      "contents_url": "https://api.github.com/repos/team-mirai/policy/contents/11_%E3%82%B9%E3%83%86%E3%83%83%E3%83%97%EF%BC%91%E6%95%99%E8%82%B2.md?ref=4e5b5193e40106166d57a96e42a388417621358c",
      "patch": "@@ -70,6 +70,7 @@\n \n ### 政策概要\n \n+* 地方自治体の行政職（窓口業務等）の人員をデジタル化等により効率化・削減し、その人件費を教育現場の人員増強に充当します。まずは喫緊の課題である教員不足を解消するため教員採用数を大幅に増やし、続いて学校事務職員やICT支援員、校務補助員などの専門スタッフを増員することで、教員の授業外業務を削減します。\n * IT/AIツールや追加の人員配置により、教員の授業外業務を削減します。  \n   * 補助金等を活用し、校務支援ツールを積極的に導入します。  \n   * 各自治体の教育委員会にデジタル推進委員を配備し、各校への円滑なテクノロジー導入を支援します。  \n@@ -184,4 +185,4 @@\n * AIを活用すれば、あらかじめ問題を検知し、行政から積極的に問題解決のための行動を起こすことができます（プッシュ型支援）。\n * 教育現場における様々な課題解決のため、実証されたアルゴリズムの活用を推進します。  \n * 今後、更なるアルゴリズムの活用可能性を探り、教育の質の向上や機会の均等化に繋がる具体的な政策を検討していきます。   \n-  * 例：個々の学習進度に合わせた教材推薦アルゴリズム、特別な支援が必要な生徒の早期発見アルゴリズムなど。\n+  * 例：個々の学習進度に合わせた教材推薦アルゴリズム、特別な支援が必要な生徒の早期発見アルゴリズムなど。\n\\ No newline at end of file"
    }
  ],
  "commits": [
    {
      "sha": "4e5b5193e40106166d57a96e42a388417621358c",
      "node_id": "C_kwDOOqTJvNoAKDRlNWI1MTkzZTQwMTA2MTY2ZDU3YTk2ZTQyYTM4ODQxNzYyMTM1OGM",
      "commit": {
        "author": {
          "name": "idobata-policy-app[bot]",
          "email": "211775619+idobata-policy-app[bot]@users.noreply.github.com",
          "date": "2025-06-12T22:57:13Z"
        },
        "committer": {
          "name": "GitHub",
          "email": "noreply@github.com",
          "date": "2025-06-12T22:57:13Z"
        },
        "message": "木村準一さんの提案に基づき、教員不足対策として行政職からの人員再配置案を「２）デジタルによる教員の働き方改革を進めます」の政策概要に追加",
        "tree": {
          "sha": "078b9c967b4e4d9d30239416f4dbcc26c0d57bd0",
          "url": "https://api.github.com/repos/team-mirai/policy/git/trees/078b9c967b4e4d9d30239416f4dbcc26c0d57bd0"
        },
        "url": "https://api.github.com/repos/team-mirai/policy/git/commits/4e5b5193e40106166d57a96e42a388417621358c",
        "comment_count": 0,
        "verification": {
          "verified": true,
          "reason": "valid",
          "signature": "-----BEGIN PGP SIGNATURE-----\n\nwsFcBAABCAAQBQJoS1tJCRC1aQ7uu5UhlAAApw0QAEYkZ3BbFGm933gN5aehfa+R\nnTnm32HmAS9qWMq+yibapCI7vKWPUUDFPSP5G3aCmYS4FFzWbTX1mb6gvdL5ASGE\n+nAerZPjkLhESVNkZcgUmHSTFY6E90myVlUsb0jskxljTPbNOv8Adun7fmB90fVK\nNWwebBXHcfgUl0t/nEezfDW7StKY1c2fl7zt2YsqQc9gRVlHONgXaLFVvZF2DOXM\n8vvhJcPIQGpd01K3oF9vjAlIk6SiRihXVpeO8YEg9ed+UWE28LkOpOvsb7GKkn7Z\nw0Ju12eVWx5ZmvNC53as+HQY487NowMYg05AnxhmfHC4Rp7k2TMV4puEWZ8MwtAi\nZm7qHXsJYd1EXSTJRQVtXdNx2G1GE4fflVN/+EXxeoVLOVKMUwxw9XeAF5fke0/F\nhlbphd5pxtPwm+TMDkQACH+IWEK2NCJk5vJcejUd87lbGIaL53QPZ0YCo9puquRJ\nhaCjB1MV6f0a4Xs14zUCYLPA6k568oeXdmRNNiTFT5+WsUUHKakO/PLc1cJE4uo/\n859Ut6oHc2tpoy+vTYcC4utADUmSnwkZ2xw83oL10jIRAh1LfYKcdBv67e+7S+uF\n6J4W9kJ0Yl8zOVYAnP3rVUedIm5GCFcd7thUSQZshztm/PiNiQEerzYczkB05Wmi\nJddw9dFWRwyvj82h0rHY\n=3oie\n-----END PGP SIGNATURE-----\n",
          "payload": "tree 078b9c967b4e4d9d30239416f4dbcc26c0d57bd0\nparent 3139d71404e4b0bdf5df1031746bab8ac93f9d71\nauthor idobata-policy-app[bot] <211775619+idobata-policy-app[bot]@users.noreply.github.com> 1749769033 +0000\ncommitter GitHub <noreply@github.com> 1749769033 +0000\n\n木村準一さんの提案に基づき、教員不足対策として行政職からの人員再配置案を「２）デジタルによる教員の働き方改革を進めます」の政策概要に追加",
          "verified_at": "2025-06-12T22:57:13Z"
        }
      },
      "url": "https://api.github.com/repos/team-mirai/policy/commits/4e5b5193e40106166d57a96e42a388417621358c",
      "html_url": "https://github.com/team-mirai/policy/commit/4e5b5193e40106166d57a96e42a388417621358c",
      "comments_url": "https://api.github.com/repos/team-mirai/policy/commits/4e5b5193e40106166d57a96e42a388417621358c/comments",
      "author": {
        "login": "idobata-policy-app[bot]",
        "id": 211775619,
        "node_id": "BOT_kgDODJ9wgw",
        "avatar_url": "https://avatars.githubusercontent.com/u/210232249?v=4",
        "gravatar_id": "",
        "url": "https://api.github.com/users/idobata-policy-app%5Bbot%5D",
        "html_url": "https://github.com/apps/idobata-policy-app",
        "followers_url": "https://api.github.com/users/idobata-policy-app%5Bbot%5D/followers",
        "following_url": "https://api.github.com/users/idobata-policy-app%5Bbot%5D/following{/other_user}",
        "gists_url": "https://api.github.com/users/idobata-policy-app%5Bbot%5D/gists{/gist_id}",
        "starred_url": "https://api.github.com/users/idobata-policy-app%5Bbot%5D/starred{/owner}{/repo}",
        "subscriptions_url": "https://api.github.com/users/idobata-policy-app%5Bbot%5D/subscriptions",
        "organizations_url": "https://api.github.com/users/idobata-policy-app%5Bbot%5D/orgs",
        "repos_url": "https://api.github.com/users/idobata-policy-app%5Bbot%5D/repos",
        "events_url": "https://api.github.com/users/idobata-policy-app%5Bbot%5D/events{/privacy}",
        "received_events_url": "https://api.github.com/users/idobata-policy-app%5Bbot%5D/received_events",
        "type": "Bot",
        "user_view_type": "public",
        "site_admin": false
      },
      "committer": {
        "login": "web-flow",
        "id": 19864447,
        "node_id": "MDQ6VXNlcjE5ODY0NDQ3",
        "avatar_url": "https://avatars.githubusercontent.com/u/19864447?v=4",
        "gravatar_id": "",
        "url": "https://api.github.com/users/web-flow",
        "html_url": "https://github.com/web-flow",
        "followers_url": "https://api.github.com/users/web-flow/followers",
        "following_url": "https://api.github.com/users/web-flow/following{/other_user}",
        "gists_url": "https://api.github.com/users/web-flow/gists{/gist_id}",
        "starred_url": "https://api.github.com/users/web-flow/starred{/owner}{/repo}",
        "subscriptions_url": "https://api.github.com/users/web-flow/subscriptions",
        "organizations_url": "https://api.github.com/users/web-flow/orgs",
        "repos_url": "https://api.github.com/users/web-flow/repos",
        "events_url": "https://api.github.com/users/web-flow/events{/privacy}",
        "received_events_url": "https://api.github.com/users/web-flow/received_events",
        "type": "User",
        "user_view_type": "public",
        "site_admin": false
      },
      "parents": [
        {
          "sha": "3139d71404e4b0bdf5df1031746bab8ac93f9d71",
          "url": "https://api.github.com/repos/team-mirai/policy/commits/3139d71404e4b0bdf5df1031746bab8ac93f9d71",
          "html_url": "https://github.com/team-mirai/policy/commit/3139d71404e4b0bdf5df1031746bab8ac93f9d71"
        }
      ]
    }
  ],
  "collected_at": "2025-06-13T02:47:34.807950"
}