{
  "basic_info": {
    "number": 3674,
    "title": "「くらべてマニ研」分類の導入による政策の体系化",
    "state": "open",
    "created_at": "2025-07-04T17:00:59Z",
    "updated_at": "2025-07-05T15:19:08Z",
    "closed_at": null,
    "merged_at": null,
    "html_url": "https://github.com/team-mirai/policy/pull/3674",
    "user": {
      "login": "idobata-policy-app[bot]",
      "id": 211775619,
      "html_url": "https://github.com/apps/idobata-policy-app"
    }
  },
  "labels": [
    {
      "id": 8639493796,
      "node_id": "LA_kwDOOqTJvM8AAAACAvQ2pA",
      "url": "https://api.github.com/repos/team-mirai/policy/labels/README",
      "name": "README",
      "color": "6F543C",
      "default": false,
      "description": ""
    }
  ],
  "comments": [],
  "review_comments": [],
  "files": [
    {
      "sha": "a3e4e52735af09383e303500ea4f96a7f8135008",
      "filename": "README.md",
      "status": "modified",
      "additions": 17,
      "deletions": 17,
      "changes": 34,
      "blob_url": "https://github.com/team-mirai/policy/blob/491ff5c5f20ee37da3e083ebf80ee90f5c5ef1d0/README.md",
      "raw_url": "https://github.com/team-mirai/policy/raw/491ff5c5f20ee37da3e083ebf80ee90f5c5ef1d0/README.md",
      "contents_url": "https://api.github.com/repos/team-mirai/policy/contents/README.md?ref=491ff5c5f20ee37da3e083ebf80ee90f5c5ef1d0",
      "patch": "@@ -11,25 +11,25 @@\n * [チームみらいのビジョン](01_チームみらいのビジョン.md)  \n * [政策インデックス](02_政策インデックス.md)  \n * [ステップ１「デジタル時代の当たり前をやりきる」](10_ステップ１「デジタル時代の当たり前をやりきる」.md)  \n-  * [１．教育](11_ステップ１教育.md)  \n-  * [２．子育て](12_ステップ１子育て.md)  \n-  * [３．くらしと行政](13_ステップ１くらしと行政.md)  \n-  * [４．産業](14_ステップ１産業.md)  \n-  * [５．科学技術](15_ステップ１科学技術.md)  \n-  * [６．デジタル民主主義](16_ステップ１デジタル民主主義.md)  \n-  * [７．医療](17_ステップ１医療.md)  \n+  * [１．教育](11_ステップ１教育.md)（子育て・教育）\n+  * [２．子育て](12_ステップ１子育て.md)（子育て・教育）\n+  * [３．くらしと行政](13_ステップ１くらしと行政.md)（行政改革・地方分権）\n+  * [４．産業](14_ステップ１産業.md)（経済・雇用・産業）\n+  * [５．科学技術](15_ステップ１科学技術.md)（科学技術・デジタル社会）\n+  * [６．デジタル民主主義](16_ステップ１デジタル民主主義.md)（科学技術・デジタル社会）\n+  * [７．医療](17_ステップ１医療.md)（医療・保健・福祉）\n * [ステップ２「変化に対応できる、しなやかな仕組みづくり」](20_ステップ２「変化に対応できるしなやかな仕組みづくり」.md)  \n-  * [１．教育](21_ステップ２教育.md)  \n-  * [２．くらしと行政](22_ステップ２くらしと行政.md)  \n-  * [３．産業](23_ステップ２産業.md)  \n-  * [４．医療](24_ステップ２医療.md)  \n+  * [１．教育](21_ステップ２教育.md)（子育て・教育）\n+  * [２．くらしと行政](22_ステップ２くらしと行政.md)（行政改革・地方分権）\n+  * [３．産業](23_ステップ２産業.md)（経済・雇用・産業）\n+  * [４．医療](24_ステップ２医療.md)（医療・保健・福祉）\n * [ステップ３「長期の成長に大胆に投資する」](30_ステップ３「長期の成長に大胆に投資する」.md)  \n-  * [１．子育て](31_ステップ３子育て.md)  \n-  * [２．教育](32_ステップ３教育.md)  \n-  * [３．科学技術](33_ステップ３科学技術.md)  \n-  * [４．産業](34_ステップ３産業.md)  \n-  * [５．エネルギー](35_ステップ３エネルギー.md)  \n-  * [６．経済財政](36_ステップ３経済財政.md)  \n+  * [１．子育て](31_ステップ３子育て.md)（子育て・教育）\n+  * [２．教育](32_ステップ３教育.md)（子育て・教育）\n+  * [３．科学技術](33_ステップ３科学技術.md)（科学技術・デジタル社会）\n+  * [４．産業](34_ステップ３産業.md)（経済・雇用・産業）\n+  * [５．エネルギー](35_ステップ３エネルギー.md)（環境・エネルギー）\n+  * [６．経済財政](36_ステップ３経済財政.md)（財政・税制）\n * [国政政党成立後１００日プラン](40_国政政党成立後100日プラン.md)  \n * [その他重要分野についての政策・ビジョン](50_国政のその他重要分野.md)\n "
    }
  ],
  "commits": [
    {
      "sha": "531c481f26168be4bae9981e94fd14faac8ec870",
      "node_id": "C_kwDOOqTJvNoAKDUzMWM0ODFmMjYxNjhiZTRiYWU5OTgxZTk0ZmQxNGZhYWM4ZWM4NzA",
      "commit": {
        "author": {
          "name": "idobata-policy-app[bot]",
          "email": "211775619+idobata-policy-app[bot]@users.noreply.github.com",
          "date": "2025-07-04T16:58:50Z"
        },
        "committer": {
          "name": "GitHub",
          "email": "noreply@github.com",
          "date": "2025-07-04T16:58:50Z"
        },
        "message": "構想主義の立場よりさんの提案に基づき、目次にマニ研分類を追記",
        "tree": {
          "sha": "47adf4216340ed62c4489d0d81baa99c5c986a3e",
          "url": "https://api.github.com/repos/team-mirai/policy/git/trees/47adf4216340ed62c4489d0d81baa99c5c986a3e"
        },
        "url": "https://api.github.com/repos/team-mirai/policy/git/commits/531c481f26168be4bae9981e94fd14faac8ec870",
        "comment_count": 0,
        "verification": {
          "verified": true,
          "reason": "valid",
          "signature": "-----BEGIN PGP SIGNATURE-----\n\nwsFcBAABCAAQBQJoaAhKCRC1aQ7uu5UhlAAA8Q4QAFoaXYKpSMZjpSdTpxRV8o4N\n7fGJqTitDXC8th1IIl+GjRKza3oTt2XXyUqVLnfWW5x6lHALvYSR+K8uKmjVHPwh\ngGjaPGejNLN7OyBVyGjyNDgZ+m0d9hXt10DygfKAs3JEmt9nrERBbyEOwv/t5cju\nJ2XhLQI14H1oQb3GR+KyV2+tbazvR9h7i9BtBPhKh2PIaenuy29YJ5XQJCvAK+14\n7ehIgfXCiKR1gOXlotx+dvkZvp0rnlnFqmchlzqx4Lx7uKK0W7/ruCDYzYtWq1u7\nxVP6pupk2rYWVnwN8q5ye0t2A5et7EnJ8pnCdlhlnT1flf93FGzpq15dwY2eU64h\nayUsA2y/rDK3v26YJHXQaJq1ZDxzd4tq1Mrq/SqAkATyJP7Y/GMBBFcWUIlrpsbo\nd6mzVB8C9kcrUNujWKLI8JFVIRToaDIEi1qDYCtCWsniZwZsEnReSkYGTsYgm3lR\nK/llGvYrA5YL2AcV5hTgncA2peB8Wgt0lWmFVUJ2gQXx6XUAz7RPpp7DplzN58gw\n2gaJHM+nCAxqOo4qBrMpCxeODKx5403TWrFwvNH/M8jk1dKHNuCogXAzzElJB5vy\npyVfAXYA5LO+TvzVuTLDUG4hs9fTVzpxAnnWCKnPscGP+ae9SwjlhZ3fGoFpoUbs\nKl8PehUCatZwTYCf1HCc\n=7//h\n-----END PGP SIGNATURE-----\n",
          "payload": "tree 47adf4216340ed62c4489d0d81baa99c5c986a3e\nparent df65ae5293022c494abbd85260769a470411eeb4\nauthor idobata-policy-app[bot] <211775619+idobata-policy-app[bot]@users.noreply.github.com> 1751648330 +0000\ncommitter GitHub <noreply@github.com> 1751648330 +0000\n\n構想主義の立場よりさんの提案に基づき、目次にマニ研分類を追記",
          "verified_at": "2025-07-04T16:58:51Z"
        }
      },
      "url": "https://api.github.com/repos/team-mirai/policy/commits/531c481f26168be4bae9981e94fd14faac8ec870",
      "html_url": "https://github.com/team-mirai/policy/commit/531c481f26168be4bae9981e94fd14faac8ec870",
      "comments_url": "https://api.github.com/repos/team-mirai/policy/commits/531c481f26168be4bae9981e94fd14faac8ec870/comments",
      "author": {
        "login": "idobata-policy-app[bot]",
        "id": 211775619,
        "node_id": "BOT_kgDODJ9wgw",
        "avatar_url": "https://avatars.githubusercontent.com/u/210232249?v=4",
        "gravatar_id": "",
        "url": "https://api.github.com/users/idobata-policy-app%5Bbot%5D",
        "html_url": "https://github.com/apps/idobata-policy-app",
        "followers_url": "https://api.github.com/users/idobata-policy-app%5Bbot%5D/followers",
        "following_url": "https://api.github.com/users/idobata-policy-app%5Bbot%5D/following{/other_user}",
        "gists_url": "https://api.github.com/users/idobata-policy-app%5Bbot%5D/gists{/gist_id}",
        "starred_url": "https://api.github.com/users/idobata-policy-app%5Bbot%5D/starred{/owner}{/repo}",
        "subscriptions_url": "https://api.github.com/users/idobata-policy-app%5Bbot%5D/subscriptions",
        "organizations_url": "https://api.github.com/users/idobata-policy-app%5Bbot%5D/orgs",
        "repos_url": "https://api.github.com/users/idobata-policy-app%5Bbot%5D/repos",
        "events_url": "https://api.github.com/users/idobata-policy-app%5Bbot%5D/events{/privacy}",
        "received_events_url": "https://api.github.com/users/idobata-policy-app%5Bbot%5D/received_events",
        "type": "Bot",
        "user_view_type": "public",
        "site_admin": false
      },
      "committer": {
        "login": "web-flow",
        "id": 19864447,
        "node_id": "MDQ6VXNlcjE5ODY0NDQ3",
        "avatar_url": "https://avatars.githubusercontent.com/u/19864447?v=4",
        "gravatar_id": "",
        "url": "https://api.github.com/users/web-flow",
        "html_url": "https://github.com/web-flow",
        "followers_url": "https://api.github.com/users/web-flow/followers",
        "following_url": "https://api.github.com/users/web-flow/following{/other_user}",
        "gists_url": "https://api.github.com/users/web-flow/gists{/gist_id}",
        "starred_url": "https://api.github.com/users/web-flow/starred{/owner}{/repo}",
        "subscriptions_url": "https://api.github.com/users/web-flow/subscriptions",
        "organizations_url": "https://api.github.com/users/web-flow/orgs",
        "repos_url": "https://api.github.com/users/web-flow/repos",
        "events_url": "https://api.github.com/users/web-flow/events{/privacy}",
        "received_events_url": "https://api.github.com/users/web-flow/received_events",
        "type": "User",
        "user_view_type": "public",
        "site_admin": false
      },
      "parents": [
        {
          "sha": "df65ae5293022c494abbd85260769a470411eeb4",
          "url": "https://api.github.com/repos/team-mirai/policy/commits/df65ae5293022c494abbd85260769a470411eeb4",
          "html_url": "https://github.com/team-mirai/policy/commit/df65ae5293022c494abbd85260769a470411eeb4"
        }
      ]
    },
    {
      "sha": "491ff5c5f20ee37da3e083ebf80ee90f5c5ef1d0",
      "node_id": "C_kwDOOqTJvNoAKDQ5MWZmNWM1ZjIwZWUzN2RhM2UwODNlYmY4MGVlOTBmNWM1ZWYxZDA",
      "commit": {
        "author": {
          "name": "idobata-policy-app[bot]",
          "email": "211775619+idobata-policy-app[bot]@users.noreply.github.com",
          "date": "2025-07-04T17:00:58Z"
        },
        "committer": {
          "name": "GitHub",
          "email": "noreply@github.com",
          "date": "2025-07-04T17:00:58Z"
        },
        "message": "構想主義の立場よりさんによる「くらべてマニ研」分類タグの追加",
        "tree": {
          "sha": "47adf4216340ed62c4489d0d81baa99c5c986a3e",
          "url": "https://api.github.com/repos/team-mirai/policy/git/trees/47adf4216340ed62c4489d0d81baa99c5c986a3e"
        },
        "url": "https://api.github.com/repos/team-mirai/policy/git/commits/491ff5c5f20ee37da3e083ebf80ee90f5c5ef1d0",
        "comment_count": 0,
        "verification": {
          "verified": true,
          "reason": "valid",
          "signature": "-----BEGIN PGP SIGNATURE-----\n\nwsFcBAABCAAQBQJoaAjKCRC1aQ7uu5UhlAAA/G8QAKgQWqiwvoxI4n+BtvcT5a3z\nsJrr3EPsbJyfRxoEXILud9ETpD2/zh0yVGB5W+wvk/JdSDXBtHcLKL65WnHTaHp3\nQgmN2VDRcv+tNwK9SRBcYX0HwFE7ZXGi7fMopOPX95req2G1P82zZmq+IOFeZo5R\nVeE1ptQeG77itcJF66Bd9Rtl4Y5VB69yyZUgFMgIIKL72o3TIQhFpXiTHQAiAYtr\nKx4Qrvn3miSsPZ+QXGBnpG1RwkpOx/8F9q03ec7Qap1m37LQGqS9lmvgZ6lN1HPM\nwr5QkNTeliGE9VLHO+NlQ/U4p+RKiGexZPVFi2KPuWnZebDiUo8/EqCFfcEFPuQA\nRocPXznpBdGMdflxwIbYbMYoA3g+0XeptC3jrACDn0sPOvsR6pWi7/PqN2XvkzMU\nf/QVJX7JNeYRXlEc1el6rvtt+MDJcoZY3IMzz2rtMGK0gJq4rBhhbN0ptg6wtdKN\nU6yLJWV5Lke+3Je0WLFkzaMy3mJgAu+Ls+p2OsNPUi/ifHUJK9xDW4Llaw3CcWos\njtDZI4cFw5nN+i1iofsxHpkh1h6tvXTL/b8GSRY30TFXnM2lGbjvLfmxgXQ4zlvP\nOQDgOEDDeLaveVOUSHCr+MqeqBEOWCB4Th/vmpvyVbJt6mbZfX0qvOavnQbHFZ85\nfVTd2Uj3xlK9SvSsFYX8\n=htBB\n-----END PGP SIGNATURE-----\n",
          "payload": "tree 47adf4216340ed62c4489d0d81baa99c5c986a3e\nparent 531c481f26168be4bae9981e94fd14faac8ec870\nauthor idobata-policy-app[bot] <211775619+idobata-policy-app[bot]@users.noreply.github.com> 1751648458 +0000\ncommitter GitHub <noreply@github.com> 1751648458 +0000\n\n構想主義の立場よりさんによる「くらべてマニ研」分類タグの追加",
          "verified_at": "2025-07-04T17:00:58Z"
        }
      },
      "url": "https://api.github.com/repos/team-mirai/policy/commits/491ff5c5f20ee37da3e083ebf80ee90f5c5ef1d0",
      "html_url": "https://github.com/team-mirai/policy/commit/491ff5c5f20ee37da3e083ebf80ee90f5c5ef1d0",
      "comments_url": "https://api.github.com/repos/team-mirai/policy/commits/491ff5c5f20ee37da3e083ebf80ee90f5c5ef1d0/comments",
      "author": {
        "login": "idobata-policy-app[bot]",
        "id": 211775619,
        "node_id": "BOT_kgDODJ9wgw",
        "avatar_url": "https://avatars.githubusercontent.com/u/210232249?v=4",
        "gravatar_id": "",
        "url": "https://api.github.com/users/idobata-policy-app%5Bbot%5D",
        "html_url": "https://github.com/apps/idobata-policy-app",
        "followers_url": "https://api.github.com/users/idobata-policy-app%5Bbot%5D/followers",
        "following_url": "https://api.github.com/users/idobata-policy-app%5Bbot%5D/following{/other_user}",
        "gists_url": "https://api.github.com/users/idobata-policy-app%5Bbot%5D/gists{/gist_id}",
        "starred_url": "https://api.github.com/users/idobata-policy-app%5Bbot%5D/starred{/owner}{/repo}",
        "subscriptions_url": "https://api.github.com/users/idobata-policy-app%5Bbot%5D/subscriptions",
        "organizations_url": "https://api.github.com/users/idobata-policy-app%5Bbot%5D/orgs",
        "repos_url": "https://api.github.com/users/idobata-policy-app%5Bbot%5D/repos",
        "events_url": "https://api.github.com/users/idobata-policy-app%5Bbot%5D/events{/privacy}",
        "received_events_url": "https://api.github.com/users/idobata-policy-app%5Bbot%5D/received_events",
        "type": "Bot",
        "user_view_type": "public",
        "site_admin": false
      },
      "committer": {
        "login": "web-flow",
        "id": 19864447,
        "node_id": "MDQ6VXNlcjE5ODY0NDQ3",
        "avatar_url": "https://avatars.githubusercontent.com/u/19864447?v=4",
        "gravatar_id": "",
        "url": "https://api.github.com/users/web-flow",
        "html_url": "https://github.com/web-flow",
        "followers_url": "https://api.github.com/users/web-flow/followers",
        "following_url": "https://api.github.com/users/web-flow/following{/other_user}",
        "gists_url": "https://api.github.com/users/web-flow/gists{/gist_id}",
        "starred_url": "https://api.github.com/users/web-flow/starred{/owner}{/repo}",
        "subscriptions_url": "https://api.github.com/users/web-flow/subscriptions",
        "organizations_url": "https://api.github.com/users/web-flow/orgs",
        "repos_url": "https://api.github.com/users/web-flow/repos",
        "events_url": "https://api.github.com/users/web-flow/events{/privacy}",
        "received_events_url": "https://api.github.com/users/web-flow/received_events",
        "type": "User",
        "user_view_type": "public",
        "site_admin": false
      },
      "parents": [
        {
          "sha": "531c481f26168be4bae9981e94fd14faac8ec870",
          "url": "https://api.github.com/repos/team-mirai/policy/commits/531c481f26168be4bae9981e94fd14faac8ec870",
          "html_url": "https://github.com/team-mirai/policy/commit/531c481f26168be4bae9981e94fd14faac8ec870"
        }
      ]
    }
  ],
  "collected_at": "2025-07-05T16:15:06.923580"
}