{
  "basic_info": {
    "number": 4312,
    "title": "【ばさん提案】産後の母親への歯科医療支援の実現",
    "state": "open",
    "created_at": "2025-07-07T14:39:32Z",
    "updated_at": "2025-07-07T14:39:33Z",
    "closed_at": null,
    "merged_at": null,
    "html_url": "https://github.com/team-mirai/policy/pull/4312",
    "user": {
      "login": "idobata-policy-app[bot]",
      "id": 211775619,
      "html_url": "https://github.com/apps/idobata-policy-app"
    }
  },
  "labels": [],
  "comments": [],
  "review_comments": [],
  "files": [
    {
      "sha": "5533c453a19720258c0e03acb92020f9117ed962",
      "filename": "README.md",
      "status": "modified",
      "additions": 2,
      "deletions": 0,
      "changes": 2,
      "blob_url": "https://github.com/team-mirai/policy/blob/a4a2fd02f74d73626c55099ca1e8fcf4bd054988/README.md",
      "raw_url": "https://github.com/team-mirai/policy/raw/a4a2fd02f74d73626c55099ca1e8fcf4bd054988/README.md",
      "contents_url": "https://api.github.com/repos/team-mirai/policy/contents/README.md?ref=a4a2fd02f74d73626c55099ca1e8fcf4bd054988",
      "patch": "@@ -13,6 +13,7 @@\n * [ステップ１「デジタル時代の当たり前をやりきる」](10_ステップ１「デジタル時代の当たり前をやりきる」.md)  \n   * [１．教育](11_ステップ１教育.md)  \n   * [２．子育て](12_ステップ１子育て.md)  \n+    * **産後の母親への歯科医療支援の実現**\n   * [３．くらしと行政](13_ステップ１くらしと行政.md)  \n   * [４．産業](14_ステップ１産業.md)  \n   * [５．科学技術](15_ステップ１科学技術.md)  \n@@ -109,3 +110,4 @@\n ## おしゃべりできるシステム『いどばたシステム』について\n \n - [デジタル民主主義2030](https://dd2030.org)で開発した[『いどばた』](https://github.com/digitaldemocracy2030/idobata/)を活用しています\n+"
    }
  ],
  "commits": [
    {
      "sha": "b78b91a4b3f3f835f212546a8db6cbdb3f0df4fe",
      "node_id": "C_kwDOOqTJvNoAKGI3OGI5MWE0YjNmM2Y4MzVmMjEyNTQ2YThkYjZjYmRiM2YwZGY0ZmU",
      "commit": {
        "author": {
          "name": "idobata-policy-app[bot]",
          "email": "211775619+idobata-policy-app[bot]@users.noreply.github.com",
          "date": "2025-07-07T14:36:51Z"
        },
        "committer": {
          "name": "GitHub",
          "email": "noreply@github.com",
          "date": "2025-07-07T14:36:51Z"
        },
        "message": "ばさんからの提案に基づき、産後の母親への歯科医療支援について「子育て」の項目に追記",
        "tree": {
          "sha": "b8ee3e3d23ed1caea3d88ebdf630397e8b248278",
          "url": "https://api.github.com/repos/team-mirai/policy/git/trees/b8ee3e3d23ed1caea3d88ebdf630397e8b248278"
        },
        "url": "https://api.github.com/repos/team-mirai/policy/git/commits/b78b91a4b3f3f835f212546a8db6cbdb3f0df4fe",
        "comment_count": 0,
        "verification": {
          "verified": true,
          "reason": "valid",
          "signature": "-----BEGIN PGP SIGNATURE-----\n\nwsFcBAABCAAQBQJoa9uDCRC1aQ7uu5UhlAAAuWkQAFonK4nkjzByVDa9xPRwvkfd\nnHNQKt/Qg1e13ebfz8pqEh80Ph8khT7CaaaPiYY04b0CxejV9Ww/YjOCXiSz77SS\nYxu4FjyTj02vCd2K4sPk+17ixuvmLccrES96gLJCHPJ8MBW93/f63PcRQwdu32kk\nw5NaFylHexerXs7y2NKa0ETSTo6QuXR3skZrbMjIOpsIP+0RHtAC4/56h2V4W2eC\nQErHvZceMEWUR1N53fnmgcZTFjVqAZrZC4kUx5BYLDEqZr3YoTktic5foK2kT0VC\nfvIsD0rnzRnT5d0awaNf7wcNIQaWrJSs32iFBP5V8tyszIl39mdZntb9KFzs3qZZ\nde0ojdCDYASg/8Oe1y4tzLxn0JyPUrEo+kNS4HEoMWpE1rNsKXXXeluobg9H7ztj\nz2TDswCoMfiMq8wSkJE3is+2TzhfRzuDWnERK86SOerGBeHm8C2fiTNrXzkZyPbR\nsG7zJOD2LcZWQlSUy+2zCHtkO338JBstDVgSIJsJVeng+xC70v5Oj6wjsedHr6O5\nIzWcH9RemnwidKeOoHtJwodmsapXpMO8QRSo3EIGTlBoML8YOPHA49Cx7vjGWH/7\n6iTSSQk/DTW+BdefyBF2yLAJIAakN/3azCIDbB8URsuBF/P2wlsQsrk1oIc7RRyr\n2o6KMGBbXGU35SZualWr\n=CLei\n-----END PGP SIGNATURE-----\n",
          "payload": "tree b8ee3e3d23ed1caea3d88ebdf630397e8b248278\nparent d4c89ca9ba2d9f26602806ff03a6ffa355570f3d\nauthor idobata-policy-app[bot] <211775619+idobata-policy-app[bot]@users.noreply.github.com> 1751899011 +0000\ncommitter GitHub <noreply@github.com> 1751899011 +0000\n\nばさんからの提案に基づき、産後の母親への歯科医療支援について「子育て」の項目に追記",
          "verified_at": "2025-07-07T14:36:51Z"
        }
      },
      "url": "https://api.github.com/repos/team-mirai/policy/commits/b78b91a4b3f3f835f212546a8db6cbdb3f0df4fe",
      "html_url": "https://github.com/team-mirai/policy/commit/b78b91a4b3f3f835f212546a8db6cbdb3f0df4fe",
      "comments_url": "https://api.github.com/repos/team-mirai/policy/commits/b78b91a4b3f3f835f212546a8db6cbdb3f0df4fe/comments",
      "author": {
        "login": "idobata-policy-app[bot]",
        "id": 211775619,
        "node_id": "BOT_kgDODJ9wgw",
        "avatar_url": "https://avatars.githubusercontent.com/u/210232249?v=4",
        "gravatar_id": "",
        "url": "https://api.github.com/users/idobata-policy-app%5Bbot%5D",
        "html_url": "https://github.com/apps/idobata-policy-app",
        "followers_url": "https://api.github.com/users/idobata-policy-app%5Bbot%5D/followers",
        "following_url": "https://api.github.com/users/idobata-policy-app%5Bbot%5D/following{/other_user}",
        "gists_url": "https://api.github.com/users/idobata-policy-app%5Bbot%5D/gists{/gist_id}",
        "starred_url": "https://api.github.com/users/idobata-policy-app%5Bbot%5D/starred{/owner}{/repo}",
        "subscriptions_url": "https://api.github.com/users/idobata-policy-app%5Bbot%5D/subscriptions",
        "organizations_url": "https://api.github.com/users/idobata-policy-app%5Bbot%5D/orgs",
        "repos_url": "https://api.github.com/users/idobata-policy-app%5Bbot%5D/repos",
        "events_url": "https://api.github.com/users/idobata-policy-app%5Bbot%5D/events{/privacy}",
        "received_events_url": "https://api.github.com/users/idobata-policy-app%5Bbot%5D/received_events",
        "type": "Bot",
        "user_view_type": "public",
        "site_admin": false
      },
      "committer": {
        "login": "web-flow",
        "id": 19864447,
        "node_id": "MDQ6VXNlcjE5ODY0NDQ3",
        "avatar_url": "https://avatars.githubusercontent.com/u/19864447?v=4",
        "gravatar_id": "",
        "url": "https://api.github.com/users/web-flow",
        "html_url": "https://github.com/web-flow",
        "followers_url": "https://api.github.com/users/web-flow/followers",
        "following_url": "https://api.github.com/users/web-flow/following{/other_user}",
        "gists_url": "https://api.github.com/users/web-flow/gists{/gist_id}",
        "starred_url": "https://api.github.com/users/web-flow/starred{/owner}{/repo}",
        "subscriptions_url": "https://api.github.com/users/web-flow/subscriptions",
        "organizations_url": "https://api.github.com/users/web-flow/orgs",
        "repos_url": "https://api.github.com/users/web-flow/repos",
        "events_url": "https://api.github.com/users/web-flow/events{/privacy}",
        "received_events_url": "https://api.github.com/users/web-flow/received_events",
        "type": "User",
        "user_view_type": "public",
        "site_admin": false
      },
      "parents": [
        {
          "sha": "d4c89ca9ba2d9f26602806ff03a6ffa355570f3d",
          "url": "https://api.github.com/repos/team-mirai/policy/commits/d4c89ca9ba2d9f26602806ff03a6ffa355570f3d",
          "html_url": "https://github.com/team-mirai/policy/commit/d4c89ca9ba2d9f26602806ff03a6ffa355570f3d"
        }
      ]
    },
    {
      "sha": "a4a2fd02f74d73626c55099ca1e8fcf4bd054988",
      "node_id": "C_kwDOOqTJvNoAKGE0YTJmZDAyZjc0ZDczNjI2YzU1MDk5Y2ExZThmY2Y0YmQwNTQ5ODg",
      "commit": {
        "author": {
          "name": "idobata-policy-app[bot]",
          "email": "211775619+idobata-policy-app[bot]@users.noreply.github.com",
          "date": "2025-07-07T14:37:40Z"
        },
        "committer": {
          "name": "GitHub",
          "email": "noreply@github.com",
          "date": "2025-07-07T14:37:40Z"
        },
        "message": "ばさんの提案に基づき、産後歯科医療支援の項目を追加 (by ば)",
        "tree": {
          "sha": "e045a09ce0f52d6f93c1affb16635a1f4fae3083",
          "url": "https://api.github.com/repos/team-mirai/policy/git/trees/e045a09ce0f52d6f93c1affb16635a1f4fae3083"
        },
        "url": "https://api.github.com/repos/team-mirai/policy/git/commits/a4a2fd02f74d73626c55099ca1e8fcf4bd054988",
        "comment_count": 0,
        "verification": {
          "verified": true,
          "reason": "valid",
          "signature": "-----BEGIN PGP SIGNATURE-----\n\nwsFcBAABCAAQBQJoa9u0CRC1aQ7uu5UhlAAAcoYQABsmM8SZRmjLmxUnTreHEWWH\nuNrVjkhm8jGrmSzYL+m3NqOv6ld+1ee6WGZ8B0aT2oC+6Kb2IK5Gc3gg3IrsEnIr\nrrmtV4XNQii121JXu3pFERa+dy9g9maBie8LryzNWNTY0JF8iFXoMN0XAjLEsIbY\ngfiWq+Q31RorkC809A6wQ+mOCk9/hI1EHgGWe/sRYULIcljUXT1mFXEgc6BbSvCG\nH/Rwgy0gFOw+NK4YaQiB/SarmN7POiHlFOGDoa44akyMD6mA+HWFMYf9CSCFQwM9\nTVvh0woORa9kt/zdoQJBLG3gSMLg118hfGUBOgTkqSHpmSbCfHU2v07NrTlG80o0\nPpkFTVa/p/x9XqTdZPOqVHH68YWBLrOdiKw4PNSdUjECw/JHbXV9QWla+NOLI293\nsQM2M76CpGICQ8x4R3YNP5KjGCtuk0l2WCvyGXocV4s9/JibYduM9nYr07wUFDKq\njxRBayDX5R+CH516BaVZQuWvULGlbhqUa300JdXLm5yT4AdDHF+Gm7UVHRfr5IQ7\nD9Xm1bYFIPISbc6LxaV0USlNkAqGBskQkg7HjQyQkSO5YqKdxwQzufdu+vmGKOal\neh8ZCZIeYqBFowpzV/L+LHYrCdQoSF0N6UP+9487Rw+nLHhFNVVdfS2RKSWsyMCF\nvqdxtOU+ui11s5SxIF1i\n=hDLp\n-----END PGP SIGNATURE-----\n",
          "payload": "tree e045a09ce0f52d6f93c1affb16635a1f4fae3083\nparent b78b91a4b3f3f835f212546a8db6cbdb3f0df4fe\nauthor idobata-policy-app[bot] <211775619+idobata-policy-app[bot]@users.noreply.github.com> 1751899060 +0000\ncommitter GitHub <noreply@github.com> 1751899060 +0000\n\nばさんの提案に基づき、産後歯科医療支援の項目を追加 (by ば)",
          "verified_at": "2025-07-07T14:37:40Z"
        }
      },
      "url": "https://api.github.com/repos/team-mirai/policy/commits/a4a2fd02f74d73626c55099ca1e8fcf4bd054988",
      "html_url": "https://github.com/team-mirai/policy/commit/a4a2fd02f74d73626c55099ca1e8fcf4bd054988",
      "comments_url": "https://api.github.com/repos/team-mirai/policy/commits/a4a2fd02f74d73626c55099ca1e8fcf4bd054988/comments",
      "author": {
        "login": "idobata-policy-app[bot]",
        "id": 211775619,
        "node_id": "BOT_kgDODJ9wgw",
        "avatar_url": "https://avatars.githubusercontent.com/u/210232249?v=4",
        "gravatar_id": "",
        "url": "https://api.github.com/users/idobata-policy-app%5Bbot%5D",
        "html_url": "https://github.com/apps/idobata-policy-app",
        "followers_url": "https://api.github.com/users/idobata-policy-app%5Bbot%5D/followers",
        "following_url": "https://api.github.com/users/idobata-policy-app%5Bbot%5D/following{/other_user}",
        "gists_url": "https://api.github.com/users/idobata-policy-app%5Bbot%5D/gists{/gist_id}",
        "starred_url": "https://api.github.com/users/idobata-policy-app%5Bbot%5D/starred{/owner}{/repo}",
        "subscriptions_url": "https://api.github.com/users/idobata-policy-app%5Bbot%5D/subscriptions",
        "organizations_url": "https://api.github.com/users/idobata-policy-app%5Bbot%5D/orgs",
        "repos_url": "https://api.github.com/users/idobata-policy-app%5Bbot%5D/repos",
        "events_url": "https://api.github.com/users/idobata-policy-app%5Bbot%5D/events{/privacy}",
        "received_events_url": "https://api.github.com/users/idobata-policy-app%5Bbot%5D/received_events",
        "type": "Bot",
        "user_view_type": "public",
        "site_admin": false
      },
      "committer": {
        "login": "web-flow",
        "id": 19864447,
        "node_id": "MDQ6VXNlcjE5ODY0NDQ3",
        "avatar_url": "https://avatars.githubusercontent.com/u/19864447?v=4",
        "gravatar_id": "",
        "url": "https://api.github.com/users/web-flow",
        "html_url": "https://github.com/web-flow",
        "followers_url": "https://api.github.com/users/web-flow/followers",
        "following_url": "https://api.github.com/users/web-flow/following{/other_user}",
        "gists_url": "https://api.github.com/users/web-flow/gists{/gist_id}",
        "starred_url": "https://api.github.com/users/web-flow/starred{/owner}{/repo}",
        "subscriptions_url": "https://api.github.com/users/web-flow/subscriptions",
        "organizations_url": "https://api.github.com/users/web-flow/orgs",
        "repos_url": "https://api.github.com/users/web-flow/repos",
        "events_url": "https://api.github.com/users/web-flow/events{/privacy}",
        "received_events_url": "https://api.github.com/users/web-flow/received_events",
        "type": "User",
        "user_view_type": "public",
        "site_admin": false
      },
      "parents": [
        {
          "sha": "b78b91a4b3f3f835f212546a8db6cbdb3f0df4fe",
          "url": "https://api.github.com/repos/team-mirai/policy/commits/b78b91a4b3f3f835f212546a8db6cbdb3f0df4fe",
          "html_url": "https://github.com/team-mirai/policy/commit/b78b91a4b3f3f835f212546a8db6cbdb3f0df4fe"
        }
      ]
    }
  ],
  "collected_at": "2025-07-07T15:12:58.213454"
}