{
  "basic_info": {
    "number": 5803,
    "title": "AI学習アシスタントにキャリア教育の機能を追加",
    "state": "open",
    "created_at": "2025-07-12T12:44:37Z",
    "updated_at": "2025-07-12T15:19:07Z",
    "closed_at": null,
    "merged_at": null,
    "html_url": "https://github.com/team-mirai/policy/pull/5803",
    "user": {
      "login": "idobata-policy-app[bot]",
      "id": 211775619,
      "html_url": "https://github.com/apps/idobata-policy-app"
    }
  },
  "labels": [
    {
      "id": 8631770611,
      "node_id": "LA_kwDOOqTJvM8AAAACAn5d8w",
      "url": "https://api.github.com/repos/team-mirai/policy/labels/%E6%95%99%E8%82%B2",
      "name": "教育",
      "color": "E57B81",
      "default": false,
      "description": ""
    }
  ],
  "comments": [],
  "review_comments": [],
  "files": [
    {
      "sha": "f8decdd00bd6cd34e6dc6e1fc09e1b021a8fff7a",
      "filename": "11_ステップ１教育.md",
      "status": "modified",
      "additions": 2,
      "deletions": 1,
      "changes": 3,
      "blob_url": "https://github.com/team-mirai/policy/blob/84c189163da49f7a45e9293d5f6aafe181b2e708/11_%E3%82%B9%E3%83%86%E3%83%83%E3%83%97%EF%BC%91%E6%95%99%E8%82%B2.md",
      "raw_url": "https://github.com/team-mirai/policy/raw/84c189163da49f7a45e9293d5f6aafe181b2e708/11_%E3%82%B9%E3%83%86%E3%83%83%E3%83%97%EF%BC%91%E6%95%99%E8%82%B2.md",
      "contents_url": "https://api.github.com/repos/team-mirai/policy/contents/11_%E3%82%B9%E3%83%86%E3%83%83%E3%83%97%EF%BC%91%E6%95%99%E8%82%B2.md?ref=84c189163da49f7a45e9293d5f6aafe181b2e708",
      "patch": "@@ -30,7 +30,7 @@\n ### 政策概要\n \n * AIを用いた「AI学習アシスタント」「AIメンタルアシスタント」を提供します。  \n-  * AI学習アシスタントは、子ども一人ひとりの学習状況や興味関心を把握しながら、学びの個別最適化をサポートします。  \n+  * AI学習アシスタントは、子ども一人ひとりの学習状況や興味関心を把握しながら、学びの個別最適化をサポートします。キャリア教育の機能も備え、子どもたちの興味・関心と関連性の高い職業や、ロールモデルとなる社会人などを紹介し、学ぶことと将来のキャリア設計との接続を支援します。  \n     * 計算練習や英単語学習などのドリル的な活動では、個々人の習熟度に合わせたものを効率よく学ぶことができます。  \n     * 答えのない探究的な活動では、AI学習アシスタントは答えを提示せず、子どもに対して問いかけたり関連する情報を提示したりしながら、子どもの自己決定や自己理解の深化を促します。  \n     * これらの学習情報を、必要に応じて、保護者や教員、さらには校種を越えて共有することで、より包括的なサポートが可能になります。  \n@@ -185,3 +185,4 @@\n * 教育現場における様々な課題解決のため、実証されたアルゴリズムの活用を推進します。  \n * 今後、更なるアルゴリズムの活用可能性を探り、教育の質の向上や機会の均等化に繋がる具体的な政策を検討していきます。   \n   * 例：個々の学習進度に合わせた教材推薦アルゴリズム、特別な支援が必要な生徒の早期発見アルゴリズムなど。\n+"
    }
  ],
  "commits": [
    {
      "sha": "84c189163da49f7a45e9293d5f6aafe181b2e708",
      "node_id": "C_kwDOOqTJvNoAKDg0YzE4OTE2M2RhNDlmN2E0NWU5MjkzZDVmNmFhZmUxODFiMmU3MDg",
      "commit": {
        "author": {
          "name": "idobata-policy-app[bot]",
          "email": "211775619+idobata-policy-app[bot]@users.noreply.github.com",
          "date": "2025-07-12T12:42:05Z"
        },
        "committer": {
          "name": "GitHub",
          "email": "noreply@github.com",
          "date": "2025-07-12T12:42:05Z"
        },
        "message": "feat(教育): SHさんの提案に基づきAIアシスタントにキャリア教育機能を追加",
        "tree": {
          "sha": "d22bd22d8183a84e3682c43d43d57f52027df25d",
          "url": "https://api.github.com/repos/team-mirai/policy/git/trees/d22bd22d8183a84e3682c43d43d57f52027df25d"
        },
        "url": "https://api.github.com/repos/team-mirai/policy/git/commits/84c189163da49f7a45e9293d5f6aafe181b2e708",
        "comment_count": 0,
        "verification": {
          "verified": true,
          "reason": "valid",
          "signature": "-----BEGIN PGP SIGNATURE-----\n\nwsFcBAABCAAQBQJoclgdCRC1aQ7uu5UhlAAAZBYQAKfDKLh0dU69962ws2AvlsVU\nU6peN/WOW+VS57e03kvmQTrru/cVlDhptD1nHnNQIdvEYSa1+tigZHeCYbwG23kJ\ngBRX5CAEbSI+LidvNUcFMDuPwS22xGmXvRtyiHq20hg9/TZxnOofh0butICHkoEd\nvkMCkaO3niaWKxVif3GVkxYOcuKimXHIt4X7VEr9bd4XpV3WSmgptG2wpbpKEi1x\noAj23GiSTz8BZVZIxij3ZE6b6c0HwsEy2Bt9COOqswyI/dN8sGWJzXg6aiO2B+A5\nUNGOeuuHMEDvmjQB+nTU83fbDTE6cljBdA4p0rYk2ZeHreoPmySiXDqOnQXU+q4C\nQDRYdD96m0m2INfBZLLySuvSauOA6g+uzhYBKaFMQCM7fE6/rOoWQGy3PwwuBF09\nR1Ila2E2N7e67uZF9K3OmMhRyvFdszmN0uT0pKvn72dfamkaTlR75CBNHMGHs2Vv\neZvQI7/S3jeOuBXC+IgvCW6ux5H02jtG8wN/UUHSixpzmU9fddnrIO9mqHVdYPkA\n3w6+qhNcgkiplLlsq3IG6FK70S8jBMPo1fgjxM7DLjlded4xzg9eWuyZ+JpJrXSg\nTuTyRfv6zW7hV1I0ZYub1uLfZk7iUVjiTUyI1sIMty5EdpCsuEqLqVa6wIpftsqy\nqAWhiMfXDjDaBC84yoOR\n=MxWr\n-----END PGP SIGNATURE-----\n",
          "payload": "tree d22bd22d8183a84e3682c43d43d57f52027df25d\nparent 1e2a87f1619c25f70093a33c6b4e04b19b1f8ad8\nauthor idobata-policy-app[bot] <211775619+idobata-policy-app[bot]@users.noreply.github.com> 1752324125 +0000\ncommitter GitHub <noreply@github.com> 1752324125 +0000\n\nfeat(教育): SHさんの提案に基づきAIアシスタントにキャリア教育機能を追加",
          "verified_at": "2025-07-12T12:42:06Z"
        }
      },
      "url": "https://api.github.com/repos/team-mirai/policy/commits/84c189163da49f7a45e9293d5f6aafe181b2e708",
      "html_url": "https://github.com/team-mirai/policy/commit/84c189163da49f7a45e9293d5f6aafe181b2e708",
      "comments_url": "https://api.github.com/repos/team-mirai/policy/commits/84c189163da49f7a45e9293d5f6aafe181b2e708/comments",
      "author": {
        "login": "idobata-policy-app[bot]",
        "id": 211775619,
        "node_id": "BOT_kgDODJ9wgw",
        "avatar_url": "https://avatars.githubusercontent.com/u/210232249?v=4",
        "gravatar_id": "",
        "url": "https://api.github.com/users/idobata-policy-app%5Bbot%5D",
        "html_url": "https://github.com/apps/idobata-policy-app",
        "followers_url": "https://api.github.com/users/idobata-policy-app%5Bbot%5D/followers",
        "following_url": "https://api.github.com/users/idobata-policy-app%5Bbot%5D/following{/other_user}",
        "gists_url": "https://api.github.com/users/idobata-policy-app%5Bbot%5D/gists{/gist_id}",
        "starred_url": "https://api.github.com/users/idobata-policy-app%5Bbot%5D/starred{/owner}{/repo}",
        "subscriptions_url": "https://api.github.com/users/idobata-policy-app%5Bbot%5D/subscriptions",
        "organizations_url": "https://api.github.com/users/idobata-policy-app%5Bbot%5D/orgs",
        "repos_url": "https://api.github.com/users/idobata-policy-app%5Bbot%5D/repos",
        "events_url": "https://api.github.com/users/idobata-policy-app%5Bbot%5D/events{/privacy}",
        "received_events_url": "https://api.github.com/users/idobata-policy-app%5Bbot%5D/received_events",
        "type": "Bot",
        "user_view_type": "public",
        "site_admin": false
      },
      "committer": {
        "login": "web-flow",
        "id": 19864447,
        "node_id": "MDQ6VXNlcjE5ODY0NDQ3",
        "avatar_url": "https://avatars.githubusercontent.com/u/19864447?v=4",
        "gravatar_id": "",
        "url": "https://api.github.com/users/web-flow",
        "html_url": "https://github.com/web-flow",
        "followers_url": "https://api.github.com/users/web-flow/followers",
        "following_url": "https://api.github.com/users/web-flow/following{/other_user}",
        "gists_url": "https://api.github.com/users/web-flow/gists{/gist_id}",
        "starred_url": "https://api.github.com/users/web-flow/starred{/owner}{/repo}",
        "subscriptions_url": "https://api.github.com/users/web-flow/subscriptions",
        "organizations_url": "https://api.github.com/users/web-flow/orgs",
        "repos_url": "https://api.github.com/users/web-flow/repos",
        "events_url": "https://api.github.com/users/web-flow/events{/privacy}",
        "received_events_url": "https://api.github.com/users/web-flow/received_events",
        "type": "User",
        "user_view_type": "public",
        "site_admin": false
      },
      "parents": [
        {
          "sha": "1e2a87f1619c25f70093a33c6b4e04b19b1f8ad8",
          "url": "https://api.github.com/repos/team-mirai/policy/commits/1e2a87f1619c25f70093a33c6b4e04b19b1f8ad8",
          "html_url": "https://github.com/team-mirai/policy/commit/1e2a87f1619c25f70093a33c6b4e04b19b1f8ad8"
        }
      ]
    }
  ],
  "collected_at": "2025-07-12T20:16:23.918669"
}